tests/control.bam
bamread/__init__.py
bamread/read.py
bamread/src/bamread.c
bamread/src/bamread.cpython-311-x86_64-linux-gnu.so
bamread/src/bamread.pyx
bamread/src/__init__.py
bamread-0.0.20.dist-info/WHEEL
bamread-0.0.20.dist-info/METADATA
bamread-0.0.20.dist-info/top_level.txt
bamread-0.0.20.dist-info/RECORD
