Metadata-Version: 2.4
Name: bamread
Version: 0.0.20
Summary: Read bam files quickly into dataframes in Python
Author-email: Endre Bakken Stovner <endbak@pm.me>
License: MIT
Project-URL: Homepage, http://github.com/pyranges/bamread
Keywords: bioinformatics,bam,pysam
Classifier: Programming Language :: Python :: 3
Classifier: Development Status :: 4 - Beta
Classifier: Environment :: Other Environment
Classifier: Intended Audience :: Developers
Classifier: Intended Audience :: Science/Research
Classifier: License :: OSI Approved :: MIT License
Classifier: Operating System :: POSIX :: Linux
Classifier: Operating System :: MacOS :: MacOS X
Classifier: Topic :: Scientific/Engineering
Requires-Dist: scipy
Requires-Dist: numpy
Requires-Dist: natsort
Requires-Dist: pysam
Requires-Dist: pandas
Provides-Extra: dev
Requires-Dist: black; extra == "dev"
Requires-Dist: bumpver; extra == "dev"
Requires-Dist: isort; extra == "dev"
Requires-Dist: pip-tools; extra == "dev"
Requires-Dist: pytest; extra == "dev"
